pypact/__init__.py
pypact/filerecord.py
pypact/reader.py
pypact/runner.py
pypact/analysis/__init__.py
pypact/analysis/plotadapter.py
pypact/analysis/propertyplotter.py
pypact/analysis/timezone.py
pypact/input/__init__.py
pypact/input/filesfile.py
pypact/input/fispactinput.py
pypact/input/fluxesfile.py
pypact/input/groupconvert.py
pypact/input/groupstructures.py
pypact/input/inputdata.py
pypact/input/keywords.py
pypact/input/serialization.py
pypact/library/__init__.py
pypact/library/nuclidelib.py
pypact/library/projectiles.py
pypact/library/reactionlib.py
pypact/library/spectrumlib.py
pypact/library/data/spectrumlib.min.json
pypact/output/__init__.py
pypact/output/doserate.py
pypact/output/gammaspectrum.py
pypact/output/nuclide.py
pypact/output/nuclides.py
pypact/output/output.py
pypact/output/rundata.py
pypact/output/tags.py
pypact/output/timestep.py
pypact/printlib/__init__.py
pypact/printlib/printlib4.py
pypact/printlib/printlib5.py
pypact/printlib/tags.py
pypact/tools/__init__.py
pypact/tools/filesmaker.py
pypact/tools/fispactconverter.py
pypact/util/__init__.py
pypact/util/decorators.py
pypact/util/exceptions.py
pypact/util/file.py
pypact/util/jsonserializable.py
pypact/util/lines.py
pypact/util/loglevels.py
pypact/util/numerical.py
pypact/util/propertyfinder.py
pypact-1.3.7.data/scripts/fispactconverter.py
pypact-1.3.7.dist-info/LICENSE
pypact-1.3.7.dist-info/METADATA
pypact-1.3.7.dist-info/WHEEL
pypact-1.3.7.dist-info/entry_points.txt
pypact-1.3.7.dist-info/top_level.txt
pypact-1.3.7.dist-info/RECORD
