Metadata-Version: 2.1
Name: pypact
Version: 1.3.7
Summary: The package for reading and manipulating the fispact output text file.
Home-page: https://github.com/fispact/pypact
Author: UKAEA
Author-email: me@physicstom.com
License: Apache License 2.0
Requires-Python: >=3.6
License-File: LICENSE
